MANIFEST.in
README.rst
setup.py
periodic/__init__.py
periodic/mass.py
periodic/table.db
periodic/table.py
periodic.egg-info/PKG-INFO
periodic.egg-info/SOURCES.txt
periodic.egg-info/dependency_links.txt
periodic.egg-info/entry_points.txt
periodic.egg-info/requires.txt
periodic.egg-info/top_level.txt