Metadata-Version: 1.1
Name: periodic
Version: 2.1.1
Summary: A periodic table API.
Home-page: https://github.com/doubledubba/periodic
Author: Jose Luis Naranjo Gomez
Author-email: luisnaranjo733@hotmail.com
License: GNU GPL
Keywords: chem chemistry periodic table finder elements
Platform: UNKNOWN
Classifier: License :: OSI Approved :: GNU General Public License (GPL)
Classifier: Topic :: Utilities
